cookie_consent/__init__.py
cookie_consent/admin.py
cookie_consent/apps.py
cookie_consent/models.py
cookie_consent/tests.py
cookie_consent/urls.py
cookie_consent/views.py
cookie_consent/migrations/0001_initial.py
cookie_consent/migrations/__init__.py
cookie_consent/static/cookie_consent/css/README.md
cookie_consent/static/cookie_consent/css/cookie_consent.scss
cookie_consent/static/cookie_consent/css/index.css
cookie_consent/static/cookie_consent/css/index.css.map
cookie_consent/static/cookie_consent/js/main.js
cookie_consent/templates/cookie_consent/includes/consent.html
django_cookie_consent_gutsh-1.1.7.dist-info/LICENSE
django_cookie_consent_gutsh-1.1.7.dist-info/METADATA
django_cookie_consent_gutsh-1.1.7.dist-info/WHEEL
django_cookie_consent_gutsh-1.1.7.dist-info/top_level.txt
django_cookie_consent_gutsh-1.1.7.dist-info/RECORD
