Metadata-Version: 2.1
Name: django-cookie-consent-gutsh
Version: 1.1.7
Summary: Cookie consent component for any Django web-site
Home-page: https://github.com/gutsh/django-cookie-consent
Author: Artem Barskii
Author-email: Artem Barskii <artemiy.barskiy@gmail.com>
License: MIT
Project-URL: Homepage, https://github.com/gutsh/django-cookie-consent
Classifier: Programming Language :: Python :: 3
Classifier: License :: OSI Approved :: MIT License
Classifier: Operating System :: OS Independent
Classifier: Framework :: Django :: 4.0
Classifier: Topic :: Internet :: WWW/HTTP :: Dynamic Content
Requires-Python: >=3.10
License-File: LICENSE
Requires-Dist: Django>=4.0
